llama_index/llms/cohere/__init__.py
llama_index/llms/cohere/base.py
llama_index/llms/cohere/utils.py
llama_index_llms_cohere-0.7.1.dist-info/METADATA
llama_index_llms_cohere-0.7.1.dist-info/WHEEL
llama_index_llms_cohere-0.7.1.dist-info/licenses/LICENSE
llama_index_llms_cohere-0.7.1.dist-info/RECORD
